eversign/__init__.py
eversign/business.py
eversign/client.py
eversign/document.py
eversign/field.py
eversign/file.py
eversign/log.py
eversign/recipient.py
eversign/signer.py
eversign/utils.py
eversign-1.1.2.dist-info/METADATA
eversign-1.1.2.dist-info/WHEEL
eversign-1.1.2.dist-info/top_level.txt
eversign-1.1.2.dist-info/RECORD
